{"is_source_file": true, "format": "CSS", "description": "Stylesheet defining the styles for the body and code elements in the application.", "external_files": [], "external_methods": [], "published": [], "classes": [], "methods": [], "calls": [], "search-terms": ["body styles", "font settings", "code styles"], "state": 2, "file_id": 1, "knowledge_revision": 15, "git_revision": "c286543285f78727dde68d7ee27a1c2e054103c3", "hash": "6c2104b8d219ed99234ae2d6329f4357", "format-version": 4, "code-base-name": "tic_tac_toe_frontend", "filename": "tic_tac_toe_frontend/src/index.css", "revision_history": [{"15": "c286543285f78727dde68d7ee27a1c2e054103c3"}]}